uel-2.1.12.dist-info/RECORD
uel-2.1.12.dist-info/LICENSE
uel-2.1.12.dist-info/WHEEL
uel-2.1.12.dist-info/entry_points.txt
uel-2.1.12.dist-info/top_level.txt
uel-2.1.12.dist-info/METADATA
uel/binary.py
uel/version.py
uel/opcodes.py
uel/tools.py
uel/constants.py
uel/__init__.py
uel/settings.py
uel/py.typed
uel/exceptions.py
uel/instruction.py
uel/typing.py
uel/main.py
uel/__main__.py
uel/opcodes
uel/executor.py
uel/internal/uelcore_internal_exceptions.c
uel/internal/uelcore_internal_exceptions.cpython-310-darwin.so
uel/objects/object.py
uel/objects/number.py
uel/objects/__init__.py
uel/objects/string.py
uel/uelio/__init__.py
uel/uelio/uelio.py
uel/cpython/py_excepthook.py
uel/builder/token.py
uel/builder/compiler.py
uel/builder/pretty_print.py
uel/builder/__init__.py
uel/builder/codeobject.py
uel/builder/parser.py
uel/builder/position.py
uel/builder/ast.py
uel/builder/node_visitor.py
uel/builder/tokenize.py
uel/builder/precedence.py
