Metadata-Version: 2.1
Name: uel
Version: 2.1.12
Summary: A programming language
Home-page: https://user-11150.github.io/puel
Author: uel
Author-email: 3584434540@qq.com
License: UNKNOWN
Keywords: language,uel,puel,programming
Platform: UNKNOWN
License-File: LICENSE
